{
	"id": "zEjKJeOckdzkiYL",
	"json": "{\"id\":\"zEjKJeOckdzkiYL\",\"url\":\"https://www.rottentomatoes.com/m/superman_2025\",\"loadedUrl\":\"https://www.rottentomatoes.com/m/superman_2025\",\"uniqueKey\":\"https://www.rottentomatoes.com/m/superman_2025\",\"method\":\"GET\",\"noRetry\":false,\"retryCount\":1,\"errorMessages\":[\"page.$: Target page, context or browser has been closed\\n    at getText (/Users/sajanbista/Desktop/Scraping/Crawlee/Daily_Intern/1page.mjs:87:43)\\n    at PlaywrightCrawler.requestHandler (/Users/sajanbista/Desktop/Scraping/Crawlee/Daily_Intern/1page.mjs:94:34)\\n    at async wrap (/Users/sajanbista/Desktop/Scraping/Crawlee/node_modules/@apify/timeout/cjs/index.cjs:54:21)\"],\"headers\":{},\"userData\":{\"label\":\"movie\",\"__crawlee\":{\"crawlDepth\":1,\"enqueueStrategy\":\"same-hostname\",\"state\":5}}}",
	"method": "GET",
	"orderNo": 1763041440676,
	"retryCount": 1,
	"uniqueKey": "https://www.rottentomatoes.com/m/superman_2025",
	"url": "https://www.rottentomatoes.com/m/superman_2025"
}